magneticalc/API.py
magneticalc/About_Dialog.py
magneticalc/Assert_Dialog.py
magneticalc/Backend_CUDA.py
magneticalc/Backend_JIT.py
magneticalc/Backend_Types.py
magneticalc/CalculationThread.py
magneticalc/CheckForUpdates_Dialog.py
magneticalc/Comparison_Types.py
magneticalc/ConditionalDecorator.py
magneticalc/Config.py
magneticalc/Config_Group.py
magneticalc/Constants.py
magneticalc/Constraint.py
magneticalc/Constraint_Editor.py
magneticalc/Debug.py
magneticalc/Display_Widget.py
magneticalc/ExportContainer_Dialog.py
magneticalc/Field.py
magneticalc/Field_Types.py
magneticalc/Field_Widget.py
magneticalc/File_Menu.py
magneticalc/Format.py
magneticalc/GUI.py
magneticalc/Help_Menu.py
magneticalc/MagnetiCalc_Data.py
magneticalc/Menu.py
magneticalc/Metric.py
magneticalc/Metric_Presets.py
magneticalc/Metric_Widget.py
magneticalc/Model.py
magneticalc/ModelAccess.py
magneticalc/Norm_Types.py
magneticalc/Options_Menu.py
magneticalc/OverridePadding_Dialog.py
magneticalc/Parameters.py
magneticalc/Parameters_Widget.py
magneticalc/Perspective_Presets.py
magneticalc/Perspective_Widget.py
magneticalc/Project.py
magneticalc/QCheckboxConfig.py
magneticalc/QMessageBox2.py
magneticalc/QTableView2.py
magneticalc/SamplingVolume.py
magneticalc/SamplingVolume_Widget.py
magneticalc/SidebarLeft.py
magneticalc/SidebarRight.py
magneticalc/Statusbar.py
magneticalc/Theme.py
magneticalc/Usage_Dialog.py
magneticalc/Validatable.py
magneticalc/Version.py
magneticalc/View_Menu.py
magneticalc/VisPyCanvas.py
magneticalc/Wire.py
magneticalc/Wire_Menu.py
magneticalc/Wire_Presets.py
magneticalc/Wire_Widget.py
magneticalc/__init__.py
magneticalc/__main__.py
magneticalc/QtWidgets2/QButtons.py
magneticalc/QtWidgets2/QDialog2.py
magneticalc/QtWidgets2/QDoubleSpinBox2.py
magneticalc/QtWidgets2/QGroupBox2.py
magneticalc/QtWidgets2/QHBoxLayout2.py
magneticalc/QtWidgets2/QHLine.py
magneticalc/QtWidgets2/QIconLabel.py
magneticalc/QtWidgets2/QLabel2.py
magneticalc/QtWidgets2/QLayouted.py
magneticalc-1.18.1.dist-info/METADATA
magneticalc-1.18.1.dist-info/WHEEL
magneticalc-1.18.1.dist-info/entry_points.txt
magneticalc-1.18.1.dist-info/licenses/LICENSE.md
magneticalc-1.18.1.dist-info/RECORD
