Metadata-Version: 2.4
Name: magneticalc
Version: 1.18.1
Summary: Magnetostatic field calculator with OpenGL GUI
Author-email: Paul Wilhelm <paul@wilhelm.dev>
License-File: LICENSE.md
Requires-Python: <4.0,>=3.9
Requires-Dist: h5py
Requires-Dist: numba>=0.55
Requires-Dist: numpy
Requires-Dist: pyqt5
Requires-Dist: qtawesome<=1.3.1,>=1.0.0
Requires-Dist: scipy
Requires-Dist: si-prefix>=1.2.2
Requires-Dist: sty
Requires-Dist: vispy>=0.6.5
